whispyr/__init__.py
whispyr/whispyr.py
whispyr-0.3.0.dist-info/METADATA
whispyr-0.3.0.dist-info/RECORD
whispyr-0.3.0.dist-info/WHEEL
whispyr-0.3.0.dist-info/top_level.txt
