Metadata-Version: 2.1
Name: whispyr
Version: 0.3.0
Summary: a python client library for whispir.io
Home-page: https://github.com/velimir0xff/whispyr
Author: Grigory Starinkin
Author-email: starinkin@gmail.com
License: MIT license
Keywords: whispyr
Platform: UNKNOWN
Classifier: Development Status :: 4 - Beta
Classifier: Intended Audience :: Developers
Classifier: License :: OSI Approved :: MIT License
Classifier: Natural Language :: English
Classifier: Programming Language :: Python :: 2
Classifier: Programming Language :: Python :: 2.7
Classifier: Programming Language :: Python :: 3
Classifier: Programming Language :: Python :: 3.4
Classifier: Programming Language :: Python :: 3.5
Classifier: Programming Language :: Python :: 3.6
Classifier: Programming Language :: Python :: 3.7
Requires-Dist: requests
Requires-Dist: six
